{
    "faction": "Sons of Behemat - Library",
    "units": [
        {
            "unitName": "Kragnos, the End of Empires",
            "modelCount": 1,
            "healthPerModel": 18,
            "floatingDamage": 0,
            "save": 0,
            "ward": 5,
            "weapons": [
                {
                    "weaponName": "The Dread Mace",
                    "numberOfAttacks": 6,
                    "toHit": 3,
                    "toWound": 2,
                    "rend": 3,
                    "weaponDamage": 4,
                    "range": 0
                },
                {
                    "weaponName": "Tuskbreaker",
                    "numberOfAttacks": 3,
                    "toHit": 4,
                    "toWound": 2,
                    "rend": 2,
                    "weaponDamage": "D3",
                    "range": 0
                },
                {
                    "weaponName": "Hooves of Wrack and Ruin",
                    "numberOfAttacks": 6,
                    "toHit": 3,
                    "toWound": 2,
                    "rend": 1,
                    "weaponDamage": 2,
                    "range": 0
                }
            ],
            "keywords": [
                "Sons of Behemat - Library"
            ]
        },
        {
            "unitName": "Mancrusher Mob",
            "modelCount": 1,
            "healthPerModel": 12,
            "floatingDamage": 0,
            "save": 0,
            "ward": 0,
            "weapons": [
                {
                    "weaponName": "'Eadbutt",
                    "numberOfAttacks": 1,
                    "toHit": 4,
                    "toWound": 2,
                    "rend": 2,
                    "weaponDamage": 4,
                    "range": 0
                },
                {
                    "weaponName": "Throwin' Rocks",
                    "numberOfAttacks": 1,
                    "toHit": 5,
                    "toWound": 2,
                    "rend": 2,
                    "weaponDamage": "D3",
                    "range": 12
                },
                {
                    "weaponName": "Massive Club",
                    "numberOfAttacks": 4,
                    "toHit": 4,
                    "toWound": 2,
                    "rend": 1,
                    "weaponDamage": 2,
                    "range": 0
                },
                {
                    "weaponName": "Mighty Kick",
                    "numberOfAttacks": 1,
                    "toHit": 4,
                    "toWound": 2,
                    "rend": 2,
                    "weaponDamage": "D3",
                    "range": 0
                }
            ],
            "keywords": [
                "Sons of Behemat - Library"
            ]
        },
        {
            "unitName": "King Brodd",
            "modelCount": 1,
            "healthPerModel": 40,
            "floatingDamage": 0,
            "save": 0,
            "ward": 0,
            "weapons": [
                {
                    "weaponName": "Obelisk of Tor Crania",
                    "numberOfAttacks": 6,
                    "toHit": 4,
                    "toWound": 2,
                    "rend": 2,
                    "weaponDamage": 5,
                    "range": 0
                },
                {
                    "weaponName": "Death Grip",
                    "numberOfAttacks": 1,
                    "toHit": 4,
                    "toWound": 2,
                    "rend": 2,
                    "weaponDamage": "D6",
                    "range": 0
                },
                {
                    "weaponName": "Almighty Stomp",
                    "numberOfAttacks": 4,
                    "toHit": 4,
                    "toWound": 2,
                    "rend": 2,
                    "weaponDamage": "D3",
                    "range": 0
                }
            ],
            "keywords": [
                "Sons of Behemat - Library"
            ]
        },
        {
            "unitName": "Beast-smasher Mega-Gargant",
            "modelCount": 1,
            "healthPerModel": 35,
            "floatingDamage": 0,
            "save": 0,
            "ward": 0,
            "weapons": [
                {
                    "weaponName": "Menhir Club",
                    "numberOfAttacks": 5,
                    "toHit": 4,
                    "toWound": 2,
                    "rend": 2,
                    "weaponDamage": 5,
                    "range": 0
                },
                {
                    "weaponName": "Death Grip",
                    "numberOfAttacks": 1,
                    "toHit": 4,
                    "toWound": 2,
                    "rend": 2,
                    "weaponDamage": "D6",
                    "range": 0
                },
                {
                    "weaponName": "Almighty Stomp",
                    "numberOfAttacks": 4,
                    "toHit": 4,
                    "toWound": 2,
                    "rend": 2,
                    "weaponDamage": "D3",
                    "range": 0
                }
            ],
            "keywords": [
                "Sons of Behemat - Library"
            ]
        },
        {
            "unitName": "Gatebreaker Mega-Gargant",
            "modelCount": 1,
            "healthPerModel": 35,
            "floatingDamage": 0,
            "save": 0,
            "ward": 0,
            "weapons": [
                {
                    "weaponName": "Hurled Boulder",
                    "numberOfAttacks": 1,
                    "toHit": 3,
                    "toWound": 2,
                    "rend": 3,
                    "weaponDamage": 4,
                    "range": 18
                },
                {
                    "weaponName": "Death Grip",
                    "numberOfAttacks": 1,
                    "toHit": 4,
                    "toWound": 2,
                    "rend": 2,
                    "weaponDamage": "D6",
                    "range": 0
                },
                {
                    "weaponName": "Almighty Stomp",
                    "numberOfAttacks": 4,
                    "toHit": 4,
                    "toWound": 2,
                    "rend": 2,
                    "weaponDamage": "D3",
                    "range": 0
                },
                {
                    "weaponName": "Fortcrusha Flail",
                    "numberOfAttacks": 6,
                    "toHit": 4,
                    "toWound": 2,
                    "rend": 2,
                    "weaponDamage": 4,
                    "range": 0
                }
            ],
            "keywords": [
                "Sons of Behemat - Library"
            ]
        },
        {
            "unitName": "Kraken-eater Mega-Gargant",
            "modelCount": 1,
            "healthPerModel": 35,
            "floatingDamage": 0,
            "save": 0,
            "ward": 0,
            "weapons": [
                {
                    "weaponName": "Hurled Debris",
                    "numberOfAttacks": 3,
                    "toHit": 4,
                    "toWound": 3,
                    "rend": 1,
                    "weaponDamage": "D3",
                    "range": 18
                },
                {
                    "weaponName": "Death Grip",
                    "numberOfAttacks": 1,
                    "toHit": 4,
                    "toWound": 2,
                    "rend": 2,
                    "weaponDamage": "D6",
                    "range": 0
                },
                {
                    "weaponName": "Almighty Stomp",
                    "numberOfAttacks": 4,
                    "toHit": 4,
                    "toWound": 2,
                    "rend": 2,
                    "weaponDamage": "D3",
                    "range": 0
                },
                {
                    "weaponName": "Shipwrecka Warclub",
                    "numberOfAttacks": 4,
                    "toHit": 4,
                    "toWound": 2,
                    "rend": 2,
                    "weaponDamage": 4,
                    "range": 0
                }
            ],
            "keywords": [
                "Sons of Behemat - Library"
            ]
        },
        {
            "unitName": "Warstomper Mega-Gargant",
            "modelCount": 1,
            "healthPerModel": 35,
            "floatingDamage": 0,
            "save": 0,
            "ward": 0,
            "weapons": [
                {
                    "weaponName": "Death Grip",
                    "numberOfAttacks": 1,
                    "toHit": 4,
                    "toWound": 2,
                    "rend": 2,
                    "weaponDamage": "D6",
                    "range": 0
                },
                {
                    "weaponName": "Almightier Stomp",
                    "numberOfAttacks": 6,
                    "toHit": 4,
                    "toWound": 2,
                    "rend": 2,
                    "weaponDamage": "D3",
                    "range": 0
                },
                {
                    "weaponName": "Titanic Boulderclub",
                    "numberOfAttacks": 4,
                    "toHit": 4,
                    "toWound": 2,
                    "rend": 2,
                    "weaponDamage": 2,
                    "range": 0
                }
            ],
            "keywords": [
                "Sons of Behemat - Library"
            ]
        },
        {
            "unitName": "Mancrusher Gargant",
            "modelCount": 1,
            "healthPerModel": 12,
            "floatingDamage": 0,
            "save": 0,
            "ward": 0,
            "weapons": [
                {
                    "weaponName": "'Eadbutt",
                    "numberOfAttacks": 1,
                    "toHit": 4,
                    "toWound": 2,
                    "rend": 2,
                    "weaponDamage": 4,
                    "range": 0
                },
                {
                    "weaponName": "Throwin' Rocks",
                    "numberOfAttacks": 1,
                    "toHit": 5,
                    "toWound": 2,
                    "rend": 2,
                    "weaponDamage": "D3",
                    "range": 12
                },
                {
                    "weaponName": "Massive Club",
                    "numberOfAttacks": 4,
                    "toHit": 4,
                    "toWound": 2,
                    "rend": 1,
                    "weaponDamage": 2,
                    "range": 0
                },
                {
                    "weaponName": "Mighty Kick",
                    "numberOfAttacks": 1,
                    "toHit": 4,
                    "toWound": 2,
                    "rend": 2,
                    "weaponDamage": "D3",
                    "range": 0
                }
            ],
            "keywords": [
                "Sons of Behemat - Library"
            ]
        },
        {
            "unitName": "Kraken-eater Mega-Gargant (Scourge of Ghyran)",
            "modelCount": 1,
            "healthPerModel": 1,
            "floatingDamage": 0,
            "save": 0,
            "ward": 0,
            "weapons": [
                {
                    "weaponName": "Hurled Debris",
                    "numberOfAttacks": 3,
                    "toHit": 4,
                    "toWound": 3,
                    "rend": 1,
                    "weaponDamage": "D3",
                    "range": 18
                },
                {
                    "weaponName": "Death Grip",
                    "numberOfAttacks": 1,
                    "toHit": 4,
                    "toWound": 2,
                    "rend": 2,
                    "weaponDamage": "D6",
                    "range": 0
                },
                {
                    "weaponName": "Spine-shattering Stomp",
                    "numberOfAttacks": 4,
                    "toHit": 4,
                    "toWound": 2,
                    "rend": 2,
                    "weaponDamage": "D3",
                    "range": 0
                },
                {
                    "weaponName": "Shipwrecka Warclub",
                    "numberOfAttacks": 4,
                    "toHit": 4,
                    "toWound": 2,
                    "rend": 2,
                    "weaponDamage": 5,
                    "range": 0
                }
            ],
            "keywords": [
                "Sons of Behemat - Library"
            ]
        }
    ]
}